rescale4dl/__init__.py
rescale4dl/batch.py
rescale4dl/blurring.py
rescale4dl/downscaling.py
rescale4dl/morphology.py
rescale4dl/upscaling.py
rescale4dl/utils.py
rescale4dl/metrics/__init__.py
rescale4dl/metrics/binary.py
rescale4dl/metrics/fov_estimates.py
rescale4dl/metrics/instance.py
rescale4dl/metrics/metrics.py
rescale4dl/metrics/metrics_skeleton.py
rescale4dl/metrics/model_pdf_metrics.py
rescale4dl/metrics/plot.py
rescale4dl/metrics/properties.py
rescale4dl/metrics/semantic.py
rescale4dl-0.1.1.dist-info/licenses/LICENSE.txt
rescale4dl-0.1.1.dist-info/METADATA
rescale4dl-0.1.1.dist-info/WHEEL
rescale4dl-0.1.1.dist-info/top_level.txt
rescale4dl-0.1.1.dist-info/RECORD
