Metadata-Version: 2.4
Name: rescale4dl
Version: 0.1.1
Summary: My python package package
Author-email: Mariana G Ferreira <mariana.g.ferreira@itqb.unl.pt>, Bruno Saraiva <bruno.msaraiva2@gmail.com>, Ricardo Henriques <ricardo.jv.henriques@gmail.com>, Estibaliz Gómez-de-Mariscal <esgodema@gmail.com>
License: MIT
Classifier: Programming Language :: Python :: 3.10
Classifier: License :: OSI Approved :: MIT License
Classifier: Operating System :: OS Independent
Requires-Python: <=3.12
License-File: LICENSE.txt
Requires-Dist: imageio>=2.33.1
Requires-Dist: jupyter>=1.1.1
Requires-Dist: matplotlib>=3.9.2
Requires-Dist: pandas>=2.2.3
Requires-Dist: pillow>=11.0.0
Requires-Dist: pypdf>=4.2.0
Requires-Dist: scikit-image>=0.22.0
Requires-Dist: scikit-learn>=1.5.2
Requires-Dist: scipy>=1.14.1
Requires-Dist: seaborn>=0.13.2
Requires-Dist: setuptools>=68.2.2
Requires-Dist: tifffile>=2024.12.12
Requires-Dist: nanopyx>=1.0.0
Provides-Extra: all
Requires-Dist: rescale4dl[dev,test]; extra == "all"
Provides-Extra: dev
Requires-Dist: pre-commit>=3.7.0; extra == "dev"
Requires-Dist: ipykernel>=6.29.4; extra == "dev"
Requires-Dist: ruff>=0.4.3; extra == "dev"
Requires-Dist: gptrepo>=1.0.3; extra == "dev"
Requires-Dist: pdoc>=12.3.1; extra == "dev"
Requires-Dist: build; extra == "dev"
Requires-Dist: gptrepo; extra == "dev"
Provides-Extra: test
Requires-Dist: pytest>=8.2.0; extra == "test"
Requires-Dist: pytest-xdist>=3.6.1; extra == "test"
Requires-Dist: pytest-cov>=5.0.0; extra == "test"
Requires-Dist: nbmake>=1.5.3; extra == "test"
Requires-Dist: mypy>=1.10.0; extra == "test"
Dynamic: license-file
